AUTHORS
LICENSE
MANIFEST.in
README.rst
setup.py
django_intercom/__init__.py
django_intercom/models.py
django_intercom/settings.py
django_intercom/urls.py
django_intercom/views.py
django_intercom.egg-info/PKG-INFO
django_intercom.egg-info/SOURCES.txt
django_intercom.egg-info/dependency_links.txt
django_intercom.egg-info/top_level.txt
django_intercom/templates/intercom/intercom_tag.html
django_intercom/templatetags/__init__.py
django_intercom/templatetags/intercom.py